{"title":"Your Morning Fix: Rs 3,360 crore meant to bribe voters seized, world’s first dengue vaccine and more","content":"Play\n\nSmitha Nair: Editor, Lead Writer and Narrator | Crystelle Rita Nunes, Anmol Kanojia, Sanjeev Nair: Video Editors and Animators | Shayonnita Mallik: Writer and Producer | Shibika Suresh: Producer | Nayantara Narayanan: Inputs | Sannuta Raghu: Executive Producer","author":"Scroll Staff","time":"2019-05-08T06:30:00+05:30","tags":["cash seizure","sexual harassment","dengue","vaccination","Myanmar","Rakhine state"],"source":"https://scroll.in/video/922652/your-morning-fix-rs-3360-crore-meant-to-bribe-voters-seized-worlds-first-dengue-vaccine-and-more"}